taskrift/__init__.py
taskrift/__main__.py
taskrift/cli.py
taskrift/config.py
taskrift/database.py
taskrift/taskrift.py
taskrift-0.1.0.dist-info/LICENSE
taskrift-0.1.0.dist-info/METADATA
taskrift-0.1.0.dist-info/WHEEL
taskrift-0.1.0.dist-info/RECORD
