Metadata-Version: 2.1
Name: taskrift
Version: 0.1.0
Summary: A dynamic and intuitive todo CLI for seamless task management and productivity enhancement.
Author: Supreet Praharaj
Author-email: supreet.praharaj.pro@gmail.com
Requires-Python: >=3.11,<4.0
Classifier: Programming Language :: Python :: 3
Classifier: Programming Language :: Python :: 3.11
Requires-Dist: typer[all] (==0.9.0)
